myoverlay_oce4nm4n/__init__.py
myoverlay_oce4nm4n/__main__.py
myoverlay_oce4nm4n/main.py
myoverlay_oce4nm4n/side_panel_app.py
myoverlay_oce4nm4n-0.1.1.dist-info/LICENSE
myoverlay_oce4nm4n-0.1.1.dist-info/METADATA
myoverlay_oce4nm4n-0.1.1.dist-info/WHEEL
myoverlay_oce4nm4n-0.1.1.dist-info/entry_points.txt
myoverlay_oce4nm4n-0.1.1.dist-info/RECORD
