Metadata-Version: 2.3
Name: myoverlay_oce4nm4n
Version: 0.1.1
Summary: 
License: MIT
Author: Oce4nM4n
Author-email: ayushmansihag@gmail.com
Requires-Python: >=3.13
Classifier: Topic :: Utilities
Classifier: Environment :: MacOS X
Requires-Dist: appdirs (>=1.4.4,<2.0.0)
Requires-Dist: datetime (>=5.5,<6.0)
